FlaskGuard/__init__.py
FlaskGuard/flask_guard.py
FlaskGuard/request_parameter.py
flask_guard-0.0.8.dist-info/LICENSE.txt
flask_guard-0.0.8.dist-info/METADATA
flask_guard-0.0.8.dist-info/WHEEL
flask_guard-0.0.8.dist-info/top_level.txt
flask_guard-0.0.8.dist-info/RECORD
