Metadata-Version: 2.1
Name: flask-guard
Version: 0.0.8
Summary: A library for checking if JSON requests have valid data.
Home-page: https://github.com/beki1337/FlaskGuard
Author: Belmin Batic
Author-email: baticbelmin10@gmail.com
Classifier: Programming Language :: Python :: 3
Classifier: License :: OSI Approved :: MIT License
Classifier: Operating System :: OS Independent
Requires-Python: >=3.10
License-File: LICENSE.txt
